zarr_any_numcodecs/__init__.py
zarr_any_numcodecs/py.typed
zarr_any_numcodecs-0.1.3.dist-info/METADATA
zarr_any_numcodecs-0.1.3.dist-info/WHEEL
zarr_any_numcodecs-0.1.3.dist-info/entry_points.txt
zarr_any_numcodecs-0.1.3.dist-info/licenses/LICENSE
zarr_any_numcodecs-0.1.3.dist-info/RECORD
