Metadata-Version: 2.4
Name: zarr-any-numcodecs
Version: 0.1.3
Summary: Adapt any `numcodecs.abc.Codec` into a `zarr.abc.Codec`
License: Copyright (c) 2025, Juniper Tyree
License-File: LICENSE
Requires-Python: >=3.11
Requires-Dist: numcodecs<0.17,>=0.14.0
Requires-Dist: zarr~=3.0
